pynyzo/__init__.py
pynyzo/approvedcycletransaction.py
pynyzo/balancelist.py
pynyzo/balancelistitem.py
pynyzo/block.py
pynyzo/byteutil.py
pynyzo/clienthelpers.py
pynyzo/config.py
pynyzo/connection.py
pynyzo/fieldbytesize.py
pynyzo/hashutil.py
pynyzo/helpers.py
pynyzo/keyutil.py
pynyzo/message.py
pynyzo/messageobject.py
pynyzo/messagetype.py
pynyzo/pynyzo.py
pynyzo/transaction.py
pynyzo/messages/__init__.py
pynyzo/messages/blockrequest.py
pynyzo/messages/blockresponse.py
pynyzo/messages/statusresponse.py
pynyzo-0.0.16.dist-info/AUTHORS.rst
pynyzo-0.0.16.dist-info/LICENSE
pynyzo-0.0.16.dist-info/METADATA
pynyzo-0.0.16.dist-info/WHEEL
pynyzo-0.0.16.dist-info/top_level.txt
pynyzo-0.0.16.dist-info/RECORD
