Metadata-Version: 2.1
Name: pynyzo
Version: 0.0.16
Summary: A Nyzo client package for Python3.
Home-page: https://github.com/EggPool/pynyzo
Author: EggdraSyl
Author-email: dev@eggpool.net
License: MIT license
Keywords: pynyzo,nyzo,python,crypto
Platform: UNKNOWN
Classifier: Development Status :: 2 - Pre-Alpha
Classifier: Intended Audience :: Developers
Classifier: License :: OSI Approved :: MIT License
Classifier: Natural Language :: English
Classifier: Programming Language :: Python :: 2
Classifier: Programming Language :: Python :: 2.7
Classifier: Programming Language :: Python :: 3
Classifier: Programming Language :: Python :: 3.4
Classifier: Programming Language :: Python :: 3.5
Classifier: Programming Language :: Python :: 3.6
Classifier: Programming Language :: Python :: 3.7
Requires-Dist: tornado
Requires-Dist: ed25519
Requires-Dist: requests
Requires-Dist: nyzostrings (>=0.0.7)
